README.md
setup.py
createwikiuser440/__init__.py
createwikiuser440/createuser.py
createwikiuser440/setup.py
createwikiuser440.egg-info/PKG-INFO
createwikiuser440.egg-info/SOURCES.txt
createwikiuser440.egg-info/dependency_links.txt
createwikiuser440.egg-info/top_level.txt