Metadata-Version: 1.0
Name: createwikiuser440
Version: 0.1
Summary: Create a new wiki user
Home-page: UNKNOWN
Author: felixs1
Author-email: UNKNOWN
License: UNKNOWN
Platform: UNKNOWN
